clinterfacer/__init__.py
clinterfacer/__main__.py
clinterfacer/cli.py
clinterfacer/parser.py
clinterfacer/commands/__init__.py
clinterfacer/commands/create.py
clinterfacer/resources/__init__.py
clinterfacer/resources/__main__.template.py
clinterfacer/resources/logging.template.ini
clinterfacer/resources/commands/__init__.py
clinterfacer/resources/commands/__init__.template.py
clinterfacer/resources/commands/command.template.py
clinterfacer/resources/subparsers/__init__.py
clinterfacer/resources/subparsers/__init__.template.py
clinterfacer/resources/subparsers/command.template.py
clinterfacer/subparsers/__init__.py
clinterfacer/subparsers/create.py
clinterfacer/utils/__init__.py
clinterfacer/utils/handlers.py
clinterfacer/utils/types.py
clinterfacer-1.3.0.dist-info/METADATA
clinterfacer-1.3.0.dist-info/WHEEL
clinterfacer-1.3.0.dist-info/entry_points.txt
clinterfacer-1.3.0.dist-info/top_level.txt
clinterfacer-1.3.0.dist-info/RECORD
