Metadata-Version: 2.1
Name: clinterfacer
Version: 1.3.0
Summary: This framework aims to simplify the creation of Command-Line Interfaces (CLIs) using python.
Home-page: https://gitlab.com/adrianohrl/clinterfacer
Author: Adriano Henrique Rossette Leite
Author-email: adrianohrl@gmail.com
Maintainer: Adriano Henrique Rossette Leite
Maintainer-email: adrianohrl@gmail.com
License: UNKNOWN
Platform: UNKNOWN
Classifier: Intended Audience :: Developers
Classifier: Intended Audience :: System Administrators
Classifier: Intended Audience :: Science/Research
Classifier: Environment :: Console
Classifier: Programming Language :: Python :: 3.7
Classifier: Operating System :: OS Independent
Requires-Dist: colorlog (>=4.0.2)
Requires-Dist: importlib-resources (>=1.0.2)
Requires-Dist: temppathlib (>=1.0.3)
Requires-Dist: tqdm (>=4.41.1)
